<?xml version="1.0" encoding="utf-8" ?>
<hibernate-mapping
      xmlns="urn:nhibernate-mapping-2.2"
      namespace="Domain.Socioboard.Models"
      assembly="Domain.Socioboard">
  <class name="Instagramaccounts" table="Instagramaccounts" lazy="false">
    <id name="id" column="id" />
    <property name="InstagramId">
      <column name="InstagramId" />
    </property>
    <property name="AccessToken">
      <column name="AccessToken"  />
    </property>
    <property name="InsUserName">
      <column name="InsUserName"  />
    </property>
    <property name="UserId">
      <column name="UserId"  />
    </property>
    <property name="IsActive">
      <column name="IsActive"  />
    </property>
    <property name="Followers">
      <column name="Followers"  />
    </property>
    <property name="FollowedBy">
      <column name="FollowedBy"  />
    </property>
    <property name="ProfileUrl">
      <column name="ProfileUrl"  />
    </property>
    <property name="TotalImages">
      <column name="TotalImages"  />
    </property>
    <property name="lastUpdate">
      <column name="lastUpdate"/>
    </property>
    <property name="bio">
      <column name="bio"/>
    </property>
    <property name="Is90DayDataUpdated">
      <column name="Is90DayDataUpdated"/>
    </property>
    <property name="lastpagereportgenerated">
      <column name="lastpagereportgenerated"/>
    </property>
  </class>
</hibernate-mapping>